src/__init__.py
src/ai.py
src/alerts.py
src/backtesting.py
src/cli.py
src/config.py
src/data_fetcher.py
src/feature_engineering.py
src/history.py
src/launcher.py
src/logging_config.py
src/market_events.py
src/ml_models.py
src/portfolio.py
src/reporting.py
src/sec_filings.py
src/streamlit_app.py
src/technical_indicators.py
src/watchlist.py
src/agents/analyst.py
src/agents/base.py
src/agents/decision.py
src/agents/orchestrator.py
src/agents/planner.py
src/agents/researcher.py
src/rag/embeddings.py
src/rag/processor.py
src/rag/vector_store.py
stock_cli/__init__.py
stock_cli/file_paths.py
stock_tracker_cli-0.3.0.dist-info/licenses/LICENSE
stock_tracker_cli-0.3.0.dist-info/METADATA
stock_tracker_cli-0.3.0.dist-info/WHEEL
stock_tracker_cli-0.3.0.dist-info/entry_points.txt
stock_tracker_cli-0.3.0.dist-info/top_level.txt
stock_tracker_cli-0.3.0.dist-info/RECORD
