Metadata-Version: 2.4
Name: stock-tracker-cli
Version: 0.3.0
Summary: A CLI tool to track stock portfolios with AI-powered analysis and automated GitHub Actions reporting.
Author-email: Chukwuebuka Ezeokeke <ebulamicheal@gmail.com>
Project-URL: Homepage, https://github.com/Chukwuebuka-2003/stock_cli
Project-URL: Bug Tracker, https://github.com/Chukwuebuka-2003/stock_cli/issues
Classifier: Programming Language :: Python :: 3
Classifier: License :: OSI Approved :: MIT License
Classifier: Operating System :: OS Independent
Classifier: Topic :: Office/Business :: Financial :: Investment
Requires-Python: >=3.8
License-File: LICENSE
Requires-Dist: click==8.1.7
Requires-Dist: pandas
Requires-Dist: groq>=0.9.0
Requires-Dist: python-dateutil==2.8.2
Requires-Dist: appdirs>=1.4.4
Requires-Dist: tavily-python>=0.3.0
Requires-Dist: yfinance==0.2.38
Requires-Dist: twelvedata
Requires-Dist: schedule>=1.2.0
Requires-Dist: python-dotenv>=1.0.0
Requires-Dist: sec-api>=1.0.16
Requires-Dist: requests>=2.31.0
Requires-Dist: Markdown>=3.5.1
Requires-Dist: streamlit>=1.32.0
Requires-Dist: plotly>=5.19.0
Requires-Dist: matplotlib>=3.8.0
Requires-Dist: seaborn>=0.13.0
Requires-Dist: ta>=0.11.0
Requires-Dist: chromadb>=0.4.22
Requires-Dist: sentence-transformers>=2.5.1
Requires-Dist: beautifulsoup4>=4.12.3
Requires-Dist: numpy>=1.24.0
Requires-Dist: scipy>=1.12.0
Requires-Dist: scikit-learn>=1.3.0
Requires-Dist: xgboost>=2.0.0
Requires-Dist: prophet>=1.1.0
Requires-Dist: joblib>=1.3.0
Dynamic: license-file
